comparedecimal/__init__.py
comparedecimal/comparedecimal.py
comparedecimal-1.0.0.dist-info/COPYING
comparedecimal-1.0.0.dist-info/METADATA
comparedecimal-1.0.0.dist-info/WHEEL
comparedecimal-1.0.0.dist-info/entry_points.txt
comparedecimal-1.0.0.dist-info/top_level.txt
comparedecimal-1.0.0.dist-info/RECORD
