Metadata-Version: 2.1
Name: comparedecimal
Version: 1.0.0
Summary: Compare decimal representations of floating-point numbers.
Home-page: https://github.com/pont-us/comparedecimal
Author: Pontus Lurcock
Author-email: pont@talvi.net
License: GNU GPLv3+
Platform: UNKNOWN
Classifier: Development Status :: 5 - Production/Stable
Classifier: License :: OSI Approved :: GNU General Public License v3 or later (GPLv3+)
Classifier: Topic :: Scientific/Engineering :: Information Analysis
Classifier: Environment :: Console
Classifier: Programming Language :: Python :: 3
Classifier: Intended Audience :: Science/Research
